EnforceTypes/Classes.py
EnforceTypes/Combined.py
EnforceTypes/Functions.py
EnforceTypes/__init__.py
EnforceTypes/py.typed
EnforceTypes/types.py
EnforceTypes/utils.py
enforcetypes-0.0.8.dist-info/LICENSE
enforcetypes-0.0.8.dist-info/WHEEL
enforcetypes-0.0.8.dist-info/METADATA
enforcetypes-0.0.8.dist-info/RECORD
