Metadata-Version: 2.1
Name: EnforceTypes
Version: 0.0.8
Summary: Simple decorators for enforcing types during runtime.
Author-email: RivenSkaye <Riven@tae.moe>
Maintainer-email: RivenSkaye <Riven@tae.moe>
Requires-Python: >=3.7
Classifier: Intended Audience :: Developers
Classifier: License :: OSI Approved :: MIT License
Classifier: Natural Language :: English
Classifier: Operating System :: OS Independent
Classifier: Programming Language :: Python :: 3 :: Only
Classifier: Programming Language :: Python :: 3
Classifier: Programming Language :: Python :: 3.10
Classifier: Programming Language :: Python :: 3.11
Classifier: Programming Language :: Python :: 3.7
Classifier: Programming Language :: Python :: 3.8
Classifier: Programming Language :: Python :: 3.9
Classifier: Topic :: Utilities
Classifier: Typing :: Typed
Requires-Dist: typing-extensions >=4.0.0, <5
Requires-Dist: typing_inspect
Project-URL: Bug Tracker, https://github.com/RivenSkaye/EnforceTypes/issues
Project-URL: Documentation, https://github.com/RivenSkaye/EnforceTypes/blob/master/README.rst
Project-URL: Home, https://github.com/RivenSkaye/EnforceTypes
Project-URL: Source, https://github.com/RivenSkaye/EnforceTypes
